{
  "updated_at": "2026-05-22T03:55:37Z",
  "indicators": {
    "ahr999": {
      "value": 0.47,
      "display": "0.47 (定投区)",
      "triggered": false,
      "level": "定投",
      "btc_price": 77699.33,
      "updated_at": "2026-05-22T03:55:33Z"
    },
    "nupl": {
      "value": 0.308,
      "display": "NUPL 0.308",
      "triggered": false,
      "level": null,
      "updated_at": "2026-05-22T03:55:33Z"
    },
    "mvrv-zscore": {
      "value": 0.79,
      "display": "Z-Score 0.79",
      "triggered": false,
      "level": null,
      "updated_at": "2026-05-22T03:55:34Z"
    },
    "puell-multiple": {
      "value": 0.72,
      "display": "Puell 0.72",
      "triggered": false,
      "level": null,
      "updated_at": "2026-05-22T03:55:35Z"
    },
    "hash-ribbons": {
      "value": -1,
      "display": "投降中 (MA30/MA60: -2.2%)",
      "triggered": false,
      "level": "投降",
      "updated_at": "2026-05-22T03:55:35Z"
    },
    "fear-greed-crypto": {
      "value": 28,
      "display": "28 (Fear)",
      "triggered": false,
      "level": null,
      "updated_at": "2026-05-22T03:55:35Z"
    },
    "funding-rate": {
      "value": 4,
      "display": "当前 -0.0364% (8h)，连续负 4 次",
      "triggered": false,
      "level": "关注",
      "current_rate": -0.0364,
      "updated_at": "2026-05-22T03:55:36Z"
    },
    "stablecoin-supply": {
      "value": 4.8,
      "display": "$321.0B, 90d +4.8%",
      "triggered": false,
      "level": null,
      "updated_at": "2026-05-22T03:55:37Z"
    },
    "crypto-vc-funding": {
      "value": null,
      "display": "获取失败",
      "triggered": false,
      "level": null,
      "updated_at": "2026-05-22T03:55:37Z"
    },
    "vix-spike": {
      "value": 16.8,
      "display": "VIX 16.8",
      "triggered": false,
      "level": null,
      "updated_at": "2026-05-22T03:55:37Z"
    },
    "ma200-deviation": {
      "value": 9.9,
      "display": "偏离 +9.9%",
      "triggered": false,
      "level": null,
      "updated_at": "2026-05-22T03:55:37Z"
    },
    "double-drop-spy-gld": {
      "value": "0.62,-3.68",
      "display": "SPY 0.62%, GLD -3.68%",
      "triggered": false,
      "level": null,
      "updated_at": "2026-05-22T03:55:37Z"
    },
    "double-drop-spy-tlt": {
      "value": "0.62,-0.91",
      "display": "SPY 0.62%, TLT -0.91%",
      "triggered": false,
      "level": null,
      "updated_at": "2026-05-22T03:55:37Z"
    },
    "schd-qqq-ratio": {
      "value": 102.99,
      "display": "比率 102.99 (↓ QQQ 走强 (risk-on))",
      "triggered": true,
      "level": "抄底",
      "updated_at": "2026-05-22T03:55:37Z"
    },
    "miner-shutdown-price": {
      "value": null,
      "display": null,
      "triggered": false,
      "level": null
    },
    "etf-net-directional-flow": {
      "value": null,
      "display": null,
      "triggered": false,
      "level": null
    },
    "ico-market-heat": {
      "value": null,
      "display": null,
      "triggered": false,
      "level": null
    }
  }
}
